xl2csv/__init__.py
xl2csv/convert.py
xl2csv-0.1.0.dist-info/entry_points.txt
xl2csv-0.1.0.dist-info/WHEEL
xl2csv-0.1.0.dist-info/METADATA
xl2csv-0.1.0.dist-info/RECORD
